rplidar.py
setup.py
rplidar_roboticia.egg-info/PKG-INFO
rplidar_roboticia.egg-info/SOURCES.txt
rplidar_roboticia.egg-info/dependency_links.txt
rplidar_roboticia.egg-info/requires.txt
rplidar_roboticia.egg-info/top_level.txt
rplidar_roboticia.egg-info/zip-safe