Metadata-Version: 1.1
Name: rplidar-roboticia
Version: 0.9.4
Summary: Simple and lightweight module for working with RPLidar laser scanners
Home-page: https://github.com/Roboticia/RPLidar
Author: Artyom Pavlov, Julien Jehl
Author-email: julien.@roboticia.com
License: MIT
Platform: UNKNOWN
Classifier: Development Status :: 4 - Beta
Classifier: Environment :: Console
Classifier: Intended Audience :: Developers
Classifier: Intended Audience :: Education
Classifier: License :: OSI Approved :: MIT License
Classifier: Operating System :: Microsoft
Classifier: Operating System :: POSIX
Classifier: Operating System :: Unix
Classifier: Programming Language :: Python :: 2
Classifier: Programming Language :: Python :: 3
Classifier: Topic :: System :: Hardware
